Source/design/freq_div.sv
`timescale 1ns/1ps
// Este modulo es un divisor de frecuencia, el cual implenta un contador para determinar los momentos en los 
// en los que se debe conmutar la señal para que dicha señal sea de la frecuencia que se desea



module freq_div(
    input logic clk,       // Signal de reloj interno 27 MHz
    output logic clk_out,  // Signal de frecuencia deseada
    output logic x,        // Signal de control de bjt x
    output logic y);       // Signal de control de bjt y

    parameter frequency = 27_000_000;                   // Frecuencia de entrada (27 MHz)
    parameter freq_out = 500;                         // Frecuencia de salida ajustable
    parameter max_count = frequency / (2 * freq_out);   // La cuenta maxima del contador

    logic [24:0] count;  // Tamaño suficiente para almacenar max_count

    // Inicialización de los valores iniciales
    initial begin
        count = 0;
        clk_out = 0;
        x=0;
        y=1;
    end

    // Lógica para contar y generar clk_out
    always @(posedge clk) begin    // posedge clk -> flancos de subida de clk
        if (count == max_count - 1) begin
            // Se conmutan las señales de salida
            clk_out <= ~clk_out;
            x <= ~x;             
            y <= ~y;
            count <= 0;
        end 
        else begin
            count <= count + 1;
        end
    end
endmodule

Source/sim/freq_div_tb.sv
`timescale 1ps/1ps

module freq_div_tb;

    // Declaración de señales
    logic clk;           // Reloj de entrada
    logic clk_out;      // Reloj de salida del divisor de frecuencia

    // Instancia del módulo bajo prueba (DUT)
    freq_div uut (.clk(clk), .clk_out(clk_out));

    // Generador de reloj (frecuencia de 27 MHz)
    always begin
        #18.5 clk = ~clk;  // T = 1 / 27 MHz => periodo = 37ns, cada mitad del periodo 18.5ns
    end

    // Procedimiento de inicialización
    initial begin
        // Inicialización de señales
        clk = 0;

        // Monitorear el comportamiento de la salida
        $monitor("Time: %t, clk_out: %b", $time, clk_out);

        // Correr la simulación por 3 ms (aproximadamente)
        #3000000;
        $finish;
    end

    // Generación del archivo VCD
    initial begin
        $dumpfile("freq_div_tb.vcd");
        $dumpvars(0, freq_div_tb);
    end
endmodule

Source/build/freq_div_tb.vcd
$date
	Wed Mar 26 18:12:07 2025
$end
$version
	Icarus Verilog
$end
$timescale
	1ps
$end
$scope module freq_div_tb $end
$var wire 1 ! clk_out $end
$var reg 1 " clk $end
$scope module uut $end
$var wire 1 " clk $end
$var parameter 32 # freq_out $end
$var parameter 32 $ frequency $end
$var parameter 64 % max_count $end
$var reg 1 ! clk_out $end
$var reg 25 & count [24:0] $end
$var reg 1 ' x $end
$var reg 1 ( y $end
$upscope $end
$upscope $end
$enddefinitions $end
$comment Show the parameter values. $end
$dumpall
b11010010111100 %
b1100110111111110011000000 $
b1111101000 #
$end
#0
$dumpvars
1(
0'
b0 &
0"
0!
$end
#19
b1 &
1"
#38
0"
#57
b10 &
1"
#76
0"
#95
b11 &
1"
#114
0"
#133
b100 &
1"
#152
0"
#171
b101 &
1"
#190
0"
#209
b110 &
1"
#228
0"
#247
b111 &
1"
#266
0"
#285
b1000 &
1"
#304
0"
#323
b1001 &
1"
#342
0"
#361
b1010 &
1"
#380
0"
#399
b1011 &
1"
#418
0"
#437
b1100 &
1"
#456
0"
#475
b1101 &
1"
#494
0"
#513
b1110 &
1"
#532
0"
#551
b1111 &
1"
#570
0"
#589
b10000 &
1"
#608
0"
#627
b10001 &
1"
#646
0"
#665
b10010 &
1"
#684
0"
#703
b10011 &
1"
#722
0"
#741
b10100 &
1"
#760
0"
#779
b10101 &
1"
#798
0"
#817
b10110 &
1"
#836
0"
#855
b10111 &
1"
#874
0"
#893
b11000 &
1"
#912
0"
#931
b11001 &
1"
#950
0"
#969
b11010 &
1"
#988
0"
#1007
b11011 &
1"
#1026
0"
#1045
b11100 &
1"
#1064
0"
#1083
b11101 &
1"
#1102
0"
#1121
b11110 &
1"
#1140
0"
#1159
b11111 &
1"
#1178
0"
#1197
b100000 &
1"
#1216
0"
#1235
b100001 &
1"
#1254
0"
#1273
b100010 &
1"
#1292
0"
#1311
b100011 &
1"
#1330
0"
#1349
b100100 &
1"
#1368
0"
#1387
b100101 &
1"
#1406
0"
#1425
b100110 &
1"
#1444
0"
#1463
b100111 &
1"
#1482
0"
#1501
b101000 &
1"
#1520
0"
#1539
b101001 &
1"
#1558
0"
#1577
b101010 &
1"
#1596
0"
#1615
b101011 &
1"
#1634
0"
#1653
b101100 &
1"
#1672
0"
#1691
b101101 &
1"
#1710
0"
#1729
b101110 &
1"
#1748
0"
#1767
b101111 &
1"
#1786
0"
#1805
b110000 &
1"
#1824
0"
#1843
b110001 &
1"
#1862
0"
#1881
b110010 &
1"
#1900
0"
#1919
b110011 &
1"
#1938
0"
#1957
b110100 &
1"
#1976
0"
#1995
b110101 &
1"
#2014
0"
#2033
b110110 &
1"
#2052
0"
#2071
b110111 &
1"
#2090
0"
#2109
b111000 &
1"
#2128
0"
#2147
b111001 &
1"
#2166
0"
#2185
b111010 &
1"
#2204
0"
#2223
b111011 &
1"
#2242
0"
#2261
b111100 &
1"
#2280
0"
#2299
b111101 &
1"
#2318
0"
#2337
b111110 &
1"
#2356
0"
#2375
b111111 &
1"
#2394
0"
#2413
b1000000 &
1"
#2432
0"
#2451
b1000001 &
1"
#2470
0"
#2489
b1000010 &
1"
#2508
0"
#2527
b1000011 &
1"
#2546
0"
#2565
b1000100 &
1"
#2584
0"
#2603
b1000101 &
1"
#2622
0"
#2641
b1000110 &
1"
#2660
0"
#2679
b1000111 &
1"
#2698
0"
#2717
b1001000 &
1"
#2736
0"
#2755
b1001001 &
1"
#2774
0"
#2793
b1001010 &
1"
#2812
0"
#2831
b1001011 &
1"
#2850
0"
#2869
b1001100 &
1"
#2888
0"
#2907
b1001101 &
1"
#2926
0"
#2945
b1001110 &
1"
#2964
0"
#2983
b1001111 &
1"
#3002
0"
#3021
b1010000 &
1"
#3040
0"
#3059
b1010001 &
1"
#3078
0"
#3097
b1010010 &
1"
#3116
0"
#3135
b1010011 &
1"
#3154
0"
#3173
b1010100 &
1"
#3192
0"
#3211
b1010101 &
1"
#3230
0"
#3249
b1010110 &
1"
#3268
0"
#3287
b1010111 &
1"
#3306
0"
#3325
b1011000 &
1"
#3344
0"
#3363
b1011001 &
1"
#3382
0"
#3401
b1011010 &
1"
#3420
0"
#3439
b1011011 &
1"
#3458
0"
#3477
b1011100 &
1"
#3496
0"
#3515
b1011101 &
1"
#3534
0"
#3553
b1011110 &
1"
#3572
0"
#3591
b1011111 &
1"
#3610
0"
#3629
b1100000 &
1"
#3648
0"
#3667
b1100001 &
1"
#3686
0"
#3705
b1100010 &
1"
#3724
0"
#3743
b1100011 &
1"
#3762
0"
#3781
b1100100 &
1"
#3800
0"
#3819
b1100101 &
1"
#3838
0"
#3857
b1100110 &
1"
#3876
0"
#3895
b1100111 &
1"
#3914
0"
#3933
b1101000 &
1"
#3952
0"
#3971
b1101001 &
1"
#3990
0"
#4009
b1101010 &
1"
#4028
0"
#4047
b1101011 &
1"
#4066
0"
#4085
b1101100 &
1"
#4104
0"
#4123
b1101101 &
1"
#4142
0"
#4161
b1101110 &
1"
#4180
0"
#4199
b1101111 &
1"
#4218
0"
#4237
b1110000 &
1"
#4256
0"
#4275
b1110001 &
1"
#4294
0"
#4313
b1110010 &
1"
#4332
0"
#4351
b1110011 &
1"
#4370
0"
#4389
b1110100 &
1"
#4408
0"
#4427
b1110101 &
1"
#4446
0"
#4465
b1110110 &
1"
#4484
0"
#4503
b1110111 &
1"
#4522
0"
#4541
b1111000 &
1"
#4560
0"
#4579
b1111001 &
1"
#4598
0"
#4617
b1111010 &
1"
#4636
0"
#4655
b1111011 &
1"
#4674
0"
#4693
b1111100 &
1"
#4712
0"
#4731
b1111101 &
1"
#4750
0"
#4769
b1111110 &
1"
#4788
0"
#4807
b1111111 &
1"
#4826
0"
#4845
b10000000 &
1"
#4864
0"
#4883
b10000001 &
1"
#4902
0"
#4921
b10000010 &
1"
#4940
0"
#4959
b10000011 &
1"
#4978
0"
#4997
b10000100 &
1"
#5016
0"
#5035
b10000101 &
1"
#5054
0"
#5073
b10000110 &
1"
#5092
0"
#5111
b10000111 &
1"
#5130
0"
#5149
b10001000 &
1"
#5168
0"
#5187
b10001001 &
1"
#5206
0"
#5225
b10001010 &
1"
#5244
0"
#5263
b10001011 &
1"
#5282
0"
#5301
b10001100 &
1"
#5320
0"
#5339
b10001101 &
1"
#5358
0"
#5377
b10001110 &
1"
#5396
0"
#5415
b10001111 &
1"
#5434
0"
#5453
b10010000 &
1"
#5472
0"
#5491
b10010001 &
1"
#5510
0"
#5529
b10010010 &
1"
#5548
0"
#5567
b10010011 &
1"
#5586
0"
#5605
b10010100 &
1"
#5624
0"
#5643
b10010101 &
1"
#5662
0"
#5681
b10010110 &
1"
#5700
0"
#5719
b10010111 &
1"
#5738
0"
#5757
b10011000 &
1"
#5776
0"
#5795
b10011001 &
1"
#5814
0"
#5833
b10011010 &
1"
#5852
0"
#5871
b10011011 &
1"
#5890
0"
#5909
b10011100 &
1"
#5928
0"
#5947
b10011101 &
1"
#5966
0"
#5985
b10011110 &
1"
#6004
0"
#6023
b10011111 &
1"
#6042
0"
#6061
b10100000 &
1"
#6080
0"
#6099
b10100001 &
1"
#6118
0"
#6137
b10100010 &
1"
#6156
0"
#6175
b10100011 &
1"
#6194
0"
#6213
b10100100 &
1"
#6232
0"
#6251
b10100101 &
1"
#6270
0"
#6289
b10100110 &
1"
#6308
0"
#6327
b10100111 &
1"
#6346
0"
#6365
b10101000 &
1"
#6384
0"
#6403
b10101001 &
1"
#6422
0"
#6441
b10101010 &
1"
#6460
0"
#6479
b10101011 &
1"
#6498
0"
#6517
b10101100 &
1"
#6536
0"
#6555
b10101101 &
1"
#6574
0"
#6593
b10101110 &
1"
#6612
0"
#6631
b10101111 &
1"
#6650
0"
#6669
b10110000 &
1"
#6688
0"
#6707
b10110001 &
1"
#6726
0"
#6745
b10110010 &
1"
#6764
0"
#6783
b10110011 &
1"
#6802
0"
#6821
b10110100 &
1"
#6840
0"
#6859
b10110101 &
1"
#6878
0"
#6897
b10110110 &
1"
#6916
0"
#6935
b10110111 &
1"
#6954
0"
#6973
b10111000 &
1"
#6992
0"
#7011
b10111001 &
1"
#7030
0"
#7049
b10111010 &
1"
#7068
0"
#7087
b10111011 &
1"
#7106
0"
#7125
b10111100 &
1"
#7144
0"
#7163
b10111101 &
1"
#7182
0"
#7201
b10111110 &
1"
#7220
0"
#7239
b10111111 &
1"
#7258
0"
#7277
b11000000 &
1"
#7296
0"
#7315
b11000001 &
1"
#7334
0"
#7353
b11000010 &
1"
#7372
0"
#7391
b11000011 &
1"
#7410
0"
#7429
b11000100 &
1"
#7448
0"
#7467
b11000101 &
1"
#7486
0"
#7505
b11000110 &
1"
#7524
0"
#7543
b11000111 &
1"
#7562
0"
#7581
b11001000 &
1"
#7600
0"
#7619
b11001001 &
1"
#7638
0"
#7657
b11001010 &
1"
#7676
0"
#7695
b11001011 &
1"
#7714
0"
#7733
b11001100 &
1"
#7752
0"
#7771
b11001101 &
1"
#7790
0"
#7809
b11001110 &
1"
#7828
0"
#7847
b11001111 &
1"
#7866
0"
#7885
b11010000 &
1"
#7904
0"
#7923
b11010001 &
1"
#7942
0"
#7961
b11010010 &
1"
#7980
0"
#7999
b11010011 &
1"
#8018
0"
#8037
b11010100 &
1"
#8056
0"
#8075
b11010101 &
1"
#8094
0"
#8113
b11010110 &
1"
#8132
0"
#8151
b11010111 &
1"
#8170
0"
#8189
b11011000 &
1"
#8208
0"
#8227
b11011001 &
1"
#8246
0"
#8265
b11011010 &
1"
#8284
0"
#8303
b11011011 &
1"
#8322
0"
#8341
b11011100 &
1"
#8360
0"
#8379
b11011101 &
1"
#8398
0"
#8417
b11011110 &
1"
#8436
0"
#8455
b11011111 &
1"
#8474
0"
#8493
b11100000 &
1"
#8512
0"
#8531
b11100001 &
1"
#8550
0"
#8569
b11100010 &
1"
#8588
0"
#8607
b11100011 &
1"
#8626
0"
#8645
b11100100 &
1"
#8664
0"
#8683
b11100101 &
1"
#8702
0"
#8721
b11100110 &
1"
#8740
0"
#8759
b11100111 &
1"
#8778
0"
#8797
b11101000 &
1"
#8816
0"
#8835
b11101001 &
1"
#8854
0"
#8873
b11101010 &
1"
#8892
0"
#8911
b11101011 &
1"
#8930
0"
#8949
b11101100 &
1"
#8968
0"
#8987
b11101101 &
1"
#9006
0"
#9025
b11101110 &
1"
#9044
0"
#9063
b11101111 &
1"
#9082
0"
#9101
b11110000 &
1"
#9120
0"
#9139
b11110001 &
1"
#9158
0"
#9177
b11110010 &
1"
#9196
0"
#9215
b11110011 &
1"
#9234
0"
#9253
b11110100 &
1"
#9272
0"
#9291
b11110101 &
1"
#9310
0"
#9329
b11110110 &
1"
#9348
0"
#9367
b11110111 &
1"
#9386
0"
#9405
b11111000 &
1"
#9424
0"
#9443
b11111001 &
1"
#9462
0"
#9481
b11111010 &
1"
#9500
0"
#9519
b11111011 &
1"
#9538
0"
#9557
b11111100 &
1"
#9576
0"
#9595
b11111101 &
1"
#9614
0"
#9633
b11111110 &
1"
#9652
0"
#9671
b11111111 &
1"
#9690
0"
#9709
b100000000 &
1"
#9728
0"
#9747
b100000001 &
1"
#9766
0"
#9785
b100000010 &
1"
#9804
0"
#9823
b100000011 &
1"
#9842
0"
#9861
b100000100 &
1"
#9880
0"
#9899
b100000101 &
1"
#9918
0"
#9937
b100000110 &
1"
#9956
0"
#9975
b100000111 &
1"
#9994
0"
#10013
b100001000 &
1"
#10032
0"
#10051
b100001001 &
1"
#10070
0"
#10089
b100001010 &
1"
#10108
0"
#10127
b100001011 &
1"
#10146
0"
#10165
b100001100 &
1"
#10184
0"
#10203
b100001101 &
1"
#10222
0"
#10241
b100001110 &
1"
#10260
0"
#10279
b100001111 &
1"
#10298
0"
#10317
b100010000 &
1"
#10336
0"
#10355
b100010001 &
1"
#10374
0"
#10393
b100010010 &
1"
#10412
0"
#10431
b100010011 &
1"
#10450
0"
#10469
b100010100 &
1"
#10488
0"
#10507
b100010101 &
1"
#10526
0"
#10545
b100010110 &
1"
#10564
0"
#10583
b100010111 &
1"
#10602
0"
#10621
b100011000 &
1"
#10640
0"
#10659
b100011001 &
1"
#10678
0"
#10697
b100011010 &
1"
#10716
0"
#10735
b100011011 &
1"
#10754
0"
#10773
b100011100 &
1"
#10792
0"
#10811
b100011101 &
1"
#10830
0"
#10849
b100011110 &
1"
#10868
0"
#10887
b100011111 &
1"
#10906
0"
#10925
b100100000 &
1"
#10944
0"
#10963
b100100001 &
1"
#10982
0"
#11001
b100100010 &
1"
#11020
0"
#11039
b100100011 &
1"
#11058
0"
#11077
b100100100 &
1"
#11096
0"
#11115
b100100101 &
1"
#11134
0"
#11153
b100100110 &
1"
#11172
0"
#11191
b100100111 &
1"
#11210
0"
#11229
b100101000 &
1"
#11248
0"
#11267
b100101001 &
1"
#11286
0"
#11305
b100101010 &
1"
#11324
0"
#11343
b100101011 &
1"
#11362
0"
#11381
b100101100 &
1"
#11400
0"
#11419
b100101101 &
1"
#11438
0"
#11457
b100101110 &
1"
#11476
0"
#11495
b100101111 &
1"
#11514
0"
#11533
b100110000 &
1"
#11552
0"
#11571
b100110001 &
1"
#11590
0"
#11609
b100110010 &
1"
#11628
0"
#11647
b100110011 &
1"
#11666
0"
#11685
b100110100 &
1"
#11704
0"
#11723
b100110101 &
1"
#11742
0"
#11761
b100110110 &
1"
#11780
0"
#11799
b100110111 &
1"
#11818
0"
#11837
b100111000 &
1"
#11856
0"
#11875
b100111001 &
1"
#11894
0"
#11913
b100111010 &
1"
#11932
0"
#11951
b100111011 &
1"
#11970
0"
#11989
b100111100 &
1"
#12008
0"
#12027
b100111101 &
1"
#12046
0"
#12065
b100111110 &
1"
#12084
0"
#12103
b100111111 &
1"
#12122
0"
#12141
b101000000 &
1"
#12160
0"
#12179
b101000001 &
1"
#12198
0"
#12217
b101000010 &
1"
#12236
0"
#12255
b101000011 &
1"
#12274
0"
#12293
b101000100 &
1"
#12312
0"
#12331
b101000101 &
1"
#12350
0"
#12369
b101000110 &
1"
#12388
0"
#12407
b101000111 &
1"
#12426
0"
#12445
b101001000 &
1"
#12464
0"
#12483
b101001001 &
1"
#12502
0"
#12521
b101001010 &
1"
#12540
0"
#12559
b101001011 &
1"
#12578
0"
#12597
b101001100 &
1"
#12616
0"
#12635
b101001101 &
1"
#12654
0"
#12673
b101001110 &
1"
#12692
0"
#12711
b101001111 &
1"
#12730
0"
#12749
b101010000 &
1"
#12768
0"
#12787
b101010001 &
1"
#12806
0"
#12825
b101010010 &
1"
#12844
0"
#12863
b101010011 &
1"
#12882
0"
#12901
b101010100 &
1"
#12920
0"
#12939
b101010101 &
1"
#12958
0"
#12977
b101010110 &
1"
#12996
0"
#13015
b101010111 &
1"
#13034
0"
#13053
b101011000 &
1"
#13072
0"
#13091
b101011001 &
1"
#13110
0"
#13129
b101011010 &
1"
#13148
0"
#13167
b101011011 &
1"
#13186
0"
#13205
b101011100 &
1"
#13224
0"
#13243
b101011101 &
1"
#13262
0"
#13281
b101011110 &
1"
#13300
0"
#13319
b101011111 &
1"
#13338
0"
#13357
b101100000 &
1"
#13376
0"
#13395
b101100001 &
1"
#13414
0"
#13433
b101100010 &
1"
#13452
0"
#13471
b101100011 &
1"
#13490
0"
#13509
b101100100 &
1"
#13528
0"
#13547
b101100101 &
1"
#13566
0"
#13585
b101100110 &
1"
#13604
0"
#13623
b101100111 &
1"
#13642
0"
#13661
b101101000 &
1"
#13680
0"
#13699
b101101001 &
1"
#13718
0"
#13737
b101101010 &
1"
#13756
0"
#13775
b101101011 &
1"
#13794
0"
#13813
b101101100 &
1"
#13832
0"
#13851
b101101101 &
1"
#13870
0"
#13889
b101101110 &
1"
#13908
0"
#13927
b101101111 &
1"
#13946
0"
#13965
b101110000 &
1"
#13984
0"
#14003
b101110001 &
1"
#14022
0"
#14041
b101110010 &
1"
#14060
0"
#14079
b101110011 &
1"
#14098
0"
#14117
b101110100 &
1"
#14136
0"
#14155
b101110101 &
1"
#14174
0"
#14193
b101110110 &
1"
#14212
0"
#14231
b101110111 &
1"
#14250
0"
#14269
b101111000 &
1"
#14288
0"
#14307
b101111001 &
1"
#14326
0"
#14345
b101111010 &
1"
#14364
0"
#14383
b101111011 &
1"
#14402
0"
#14421
b101111100 &
1"
#14440
0"
#14459
b101111101 &
1"
#14478
0"
#14497
b101111110 &
1"
#14516
0"
#14535
b101111111 &
1"
#14554
0"
#14573
b110000000 &
1"
#14592
0"
#14611
b110000001 &
1"
#14630
0"
#14649
b110000010 &
1"
#14668
0"
#14687
b110000011 &
1"
#14706
0"
#14725
b110000100 &
1"
#14744
0"
#14763
b110000101 &
1"
#14782
0"
#14801
b110000110 &
1"
#14820
0"
#14839
b110000111 &
1"
#14858
0"
#14877
b110001000 &
1"
#14896
0"
#14915
b110001001 &
1"
#14934
0"
#14953
b110001010 &
1"
#14972
0"
#14991
b110001011 &
1"
#15010
0"
#15029
b110001100 &
1"
#15048
0"
#15067
b110001101 &
1"
#15086
0"
#15105
b110001110 &
1"
#15124
0"
#15143
b110001111 &
1"
#15162
0"
#15181
b110010000 &
1"
#15200
0"
#15219
b110010001 &
1"
#15238
0"
#15257
b110010010 &
1"
#15276
0"
#15295
b110010011 &
1"
#15314
0"
#15333
b110010100 &
1"
#15352
0"
#15371
b110010101 &
1"
#15390
0"
#15409
b110010110 &
1"
#15428
0"
#15447
b110010111 &
1"
#15466
0"
#15485
b110011000 &
1"
#15504
0"
#15523
b110011001 &
1"
#15542
0"
#15561
b110011010 &
1"
#15580
0"
#15599
b110011011 &
1"
#15618
0"
#15637
b110011100 &
1"
#15656
0"
#15675
b110011101 &
1"
#15694
0"
#15713
b110011110 &
1"
#15732
0"
#15751
b110011111 &
1"
#15770
0"
#15789
b110100000 &
1"
#15808
0"
#15827
b110100001 &
1"
#15846
0"
#15865
b110100010 &
1"
#15884
0"
#15903
b110100011 &
1"
#15922
0"
#15941
b110100100 &
1"
#15960
0"
#15979
b110100101 &
1"
#15998
0"
#16017
b110100110 &
1"
#16036
0"
#16055
b110100111 &
1"
#16074
0"
#16093
b110101000 &
1"
#16112
0"
#16131
b110101001 &
1"
#16150
0"
#16169
b110101010 &
1"
#16188
0"
#16207
b110101011 &
1"
#16226
0"
#16245
b110101100 &
1"
#16264
0"
#16283
b110101101 &
1"
#16302
0"
#16321
b110101110 &
1"
#16340
0"
#16359
b110101111 &
1"
#16378
0"
#16397
b110110000 &
1"
#16416
0"
#16435
b110110001 &
1"
#16454
0"
#16473
b110110010 &
1"
#16492
0"
#16511
b110110011 &
1"
#16530
0"
#16549
b110110100 &
1"
#16568
0"
#16587
b110110101 &
1"
#16606
0"
#16625
b110110110 &
1"
#16644
0"
#16663
b110110111 &
1"
#16682
0"
#16701
b110111000 &
1"
#16720
0"
#16739
b110111001 &
1"
#16758
0"
#16777
b110111010 &
1"
#16796
0"
#16815
b110111011 &
1"
#16834
0"
#16853
b110111100 &
1"
#16872
0"
#16891
b110111101 &
1"
#16910
0"
#16929
b110111110 &
1"
#16948
0"
#16967
b110111111 &
1"
#16986
0"
#17005
b111000000 &
1"
#17024
0"
#17043
b111000001 &
1"
#17062
0"
#17081
b111000010 &
1"
#17100
0"
#17119
b111000011 &
1"
#17138
0"
#17157
b111000100 &
1"
#17176
0"
#17195
b111000101 &
1"
#17214
0"
#17233
b111000110 &
1"
#17252
0"
#17271
b111000111 &
1"
#17290
0"
#17309
b111001000 &
1"
#17328
0"
#17347
b111001001 &
1"
#17366
0"
#17385
b111001010 &
1"
#17404
0"
#17423
b111001011 &
1"
#17442
0"
#17461
b111001100 &
1"
#17480
0"
#17499
b111001101 &
1"
#17518
0"
#17537
b111001110 &
1"
#17556
0"
#17575
b111001111 &
1"
#17594
0"
#17613
b111010000 &
1"
#17632
0"
#17651
b111010001 &
1"
#17670
0"
#17689
b111010010 &
1"
#17708
0"
#17727
b111010011 &
1"
#17746
0"
#17765
b111010100 &
1"
#17784
0"
#17803
b111010101 &
1"
#17822
0"
#17841
b111010110 &
1"
#17860
0"
#17879
b111010111 &
1"
#17898
0"
#17917
b111011000 &
1"
#17936
0"
#17955
b111011001 &
1"
#17974
0"
#17993
b111011010 &
1"
#18012
0"
#18031
b111011011 &
1"
#18050
0"
#18069
b111011100 &
1"
#18088
0"
#18107
b111011101 &
1"
#18126
0"
#18145
b111011110 &
1"
#18164
0"
#18183
b111011111 &
1"
#18202
0"
#18221
b111100000 &
1"
#18240
0"
#18259
b111100001 &
1"
#18278
0"
#18297
b111100010 &
1"
#18316
0"
#18335
b111100011 &
1"
#18354
0"
#18373
b111100100 &
1"
#18392
0"
#18411
b111100101 &
1"
#18430
0"
#18449
b111100110 &
1"
#18468
0"
#18487
b111100111 &
1"
#18506
0"
#18525
b111101000 &
1"
#18544
0"
#18563
b111101001 &
1"
#18582
0"
#18601
b111101010 &
1"
#18620
0"
#18639
b111101011 &
1"
#18658
0"
#18677
b111101100 &
1"
#18696
0"
#18715
b111101101 &
1"
#18734
0"
#18753
b111101110 &
1"
#18772
0"
#18791
b111101111 &
1"
#18810
0"
#18829
b111110000 &
1"
#18848
0"
#18867
b111110001 &
1"
#18886
0"
#18905
b111110010 &
1"
#18924
0"
#18943
b111110011 &
1"
#18962
0"
#18981
b111110100 &
1"
#19000
0"
#19019
b111110101 &
1"
#19038
0"
#19057
b111110110 &
1"
#19076
0"
#19095
b111110111 &
1"
#19114
0"
#19133
b111111000 &
1"
#19152
0"
#19171
b111111001 &
1"
#19190
0"
#19209
b111111010 &
1"
#19228
0"
#19247
b111111011 &
1"
#19266
0"
#19285
b111111100 &
1"
#19304
0"
#19323
b111111101 &
1"
#19342
0"
#19361
b111111110 &
1"
#19380
0"
#19399
b111111111 &
1"
#19418
0"
#19437
b1000000000 &
1"
#19456
0"
#19475
b1000000001 &
1"
#19494
0"
#19513
b1000000010 &
1"
#19532
0"
#19551
b1000000011 &
1"
#19570
0"
#19589
b1000000100 &
1"
#19608
0"
#19627
b1000000101 &
1"
#19646
0"
#19665
b1000000110 &
1"
#19684
0"
#19703
b1000000111 &
1"
#19722
0"
#19741
b1000001000 &
1"
#19760
0"
#19779
b1000001001 &
1"
#19798
0"
#19817
b1000001010 &
1"
#19836
0"
#19855
b1000001011 &
1"
#19874
0"
#19893
b1000001100 &
1"
#19912
0"
#19931
b1000001101 &
1"
#19950
0"
#19969
b1000001110 &
1"
#19988
0"
#20007
b1000001111 &
1"
#20026
0"
#20045
b1000010000 &
1"
#20064
0"
#20083
b1000010001 &
1"
#20102
0"
#20121
b1000010010 &
1"
#20140
0"
#20159
b1000010011 &
1"
#20178
0"
#20197
b1000010100 &
1"
#20216
0"
#20235
b1000010101 &
1"
#20254
0"
#20273
b1000010110 &
1"
#20292
0"
#20311
b1000010111 &
1"
#20330
0"
#20349
b1000011000 &
1"
#20368
0"
#20387
b1000011001 &
1"
#20406
0"
#20425
b1000011010 &
1"
#20444
0"
#20463
b1000011011 &
1"
#20482
0"
#20501
b1000011100 &
1"
#20520
0"
#20539
b1000011101 &
1"
#20558
0"
#20577
b1000011110 &
1"
#20596
0"
#20615
b1000011111 &
1"
#20634
0"
#20653
b1000100000 &
1"
#20672
0"
#20691
b1000100001 &
1"
#20710
0"
#20729
b1000100010 &
1"
#20748
0"
#20767
b1000100011 &
1"
#20786
0"
#20805
b1000100100 &
1"
#20824
0"
#20843
b1000100101 &
1"
#20862
0"
#20881
b1000100110 &
1"
#20900
0"
#20919
b1000100111 &
1"
#20938
0"
#20957
b1000101000 &
1"
#20976
0"
#20995
b1000101001 &
1"
#21014
0"
#21033
b1000101010 &
1"
#21052
0"
#21071
b1000101011 &
1"
#21090
0"
#21109
b1000101100 &
1"
#21128
0"
#21147
b1000101101 &
1"
#21166
0"
#21185
b1000101110 &
1"
#21204
0"
#21223
b1000101111 &
1"
#21242
0"
#21261
b1000110000 &
1"
#21280
0"
#21299
b1000110001 &
1"
#21318
0"
#21337
b1000110010 &
1"
#21356
0"
#21375
b1000110011 &
1"
#21394
0"
#21413
b1000110100 &
1"
#21432
0"
#21451
b1000110101 &
1"
#21470
0"
#21489
b1000110110 &
1"
#21508
0"
#21527
b1000110111 &
1"
#21546
0"
#21565
b1000111000 &
1"
#21584
0"
#21603
b1000111001 &
1"
#21622
0"
#21641
b1000111010 &
1"
#21660
0"
#21679
b1000111011 &
1"
#21698
0"
#21717
b1000111100 &
1"
#21736
0"
#21755
b1000111101 &
1"
#21774
0"
#21793
b1000111110 &
1"
#21812
0"
#21831
b1000111111 &
1"
#21850
0"
#21869
b1001000000 &
1"
#21888
0"
#21907
b1001000001 &
1"
#21926
0"
#21945
b1001000010 &
1"
#21964
0"
#21983
b1001000011 &
1"
#22002
0"
#22021
b1001000100 &
1"
#22040
0"
#22059
b1001000101 &
1"
#22078
0"
#22097
b1001000110 &
1"
#22116
0"
#22135
b1001000111 &
1"
#22154
0"
#22173
b1001001000 &
1"
#22192
0"
#22211
b1001001001 &
1"
#22230
0"
#22249
b1001001010 &
1"
#22268
0"
#22287
b1001001011 &
1"
#22306
0"
#22325
b1001001100 &
1"
#22344
0"
#22363
b1001001101 &
1"
#22382
0"
#22401
b1001001110 &
1"
#22420
0"
#22439
b1001001111 &
1"
#22458
0"
#22477
b1001010000 &
1"
#22496
0"
#22515
b1001010001 &
1"
#22534
0"
#22553
b1001010010 &
1"
#22572
0"
#22591
b1001010011 &
1"
#22610
0"
#22629
b1001010100 &
1"
#22648
0"
#22667
b1001010101 &
1"
#22686
0"
#22705
b1001010110 &
1"
#22724
0"
#22743
b1001010111 &
1"
#22762
0"
#22781
b1001011000 &
1"
#22800
0"
#22819
b1001011001 &
1"
#22838
0"
#22857
b1001011010 &
1"
#22876
0"
#22895
b1001011011 &
1"
#22914
0"
#22933
b1001011100 &
1"
#22952
0"
#22971
b1001011101 &
1"
#22990
0"
#23009
b1001011110 &
1"
#23028
0"
#23047
b1001011111 &
1"
#23066
0"
#23085
b1001100000 &
1"
#23104
0"
#23123
b1001100001 &
1"
#23142
0"
#23161
b1001100010 &
1"
#23180
0"
#23199
b1001100011 &
1"
#23218
0"
#23237
b1001100100 &
1"
#23256
0"
#23275
b1001100101 &
1"
#23294
0"
#23313
b1001100110 &
1"
#23332
0"
#23351
b1001100111 &
1"
#23370
0"
#23389
b1001101000 &
1"
#23408
0"
#23427
b1001101001 &
1"
#23446
0"
#23465
b1001101010 &
1"
#23484
0"
#23503
b1001101011 &
1"
#23522
0"
#23541
b1001101100 &
1"
#23560
0"
#23579
b1001101101 &
1"
#23598
0"
#23617
b1001101110 &
1"
#23636
0"
#23655
b1001101111 &
1"
#23674
0"
#23693
b1001110000 &
1"
#23712
0"
#23731
b1001110001 &
1"
#23750
0"
#23769
b1001110010 &
1"
#23788
0"
#23807
b1001110011 &
1"
#23826
0"
#23845
b1001110100 &
1"
#23864
0"
#23883
b1001110101 &
1"
#23902
0"
#23921
b1001110110 &
1"
#23940
0"
#23959
b1001110111 &
1"
#23978
0"
#23997
b1001111000 &
1"
#24016
0"
#24035
b1001111001 &
1"
#24054
0"
#24073
b1001111010 &
1"
#24092
0"
#24111
b1001111011 &
1"
#24130
0"
#24149
b1001111100 &
1"
#24168
0"
#24187
b1001111101 &
1"
#24206
0"
#24225
b1001111110 &
1"
#24244
0"
#24263
b1001111111 &
1"
#24282
0"
#24301
b1010000000 &
1"
#24320
0"
#24339
b1010000001 &
1"
#24358
0"
#24377
b1010000010 &
1"
#24396
0"
#24415
b1010000011 &
1"
#24434
0"
#24453
b1010000100 &
1"
#24472
0"
#24491
b1010000101 &
1"
#24510
0"
#24529
b1010000110 &
1"
#24548
0"
#24567
b1010000111 &
1"
#24586
0"
#24605
b1010001000 &
1"
#24624
0"
#24643
b1010001001 &
1"
#24662
0"
#24681
b1010001010 &
1"
#24700
0"
#24719
b1010001011 &
1"
#24738
0"
