Source/design/seg_decoder.sv
`timescale 1ns/1ps
// Este modulo recibe un numero binario de 4 bits retorna 7 bits, uno para cada segmentos del display

module seg_decoder(input logic [3:0] w, output logic [6:0] d);
    assign d[6] =  w[1] | w[3] | (~w[2] & ~w[0]) | (w[2] & w[0]);   // a
    assign d[5] = ~w[2] | w[1] | ~w[0];                            // b
    assign d[4] = ~w[1] | w[2] | w[0];                             // c
    assign d[3] = (~w[2] & ~w[0]) | (~w[2] & w[1]) + (w[1] & ~w[0]) | (w[2] & ~w[1] & w[0]) ;  // d
    assign d[2] = (~w[2] & ~w[0]) | (w[1] & ~w[0]);                // e
    assign d[1] = w[3] | (~w[1] & ~w[0]) | (w[2] & ~w[1]);         // f
    assign d[0] = w[3] | (~w[2] & w[1]) | (w[2] & ~w[0]) | (w[2] & ~w[1]);  // g
endmodule

Source/sim/disp_dec.sv
`timescale 1ns/1ps

module seg_decoder_tb;
    logic [3:0] w;         // Señal de entrada
    logic [6:0] d;      // Señal de salida

    // Instanciamos el módulo 'module_bcd_syndrome'
    seg_decoder uut (.w(w), .d(d));

    initial begin
        // 0
        w = 4'b0000; #10;
        $display("Number: %b, Segments: %b", w, d);
        
        // 1
        w = 4'b0001; #10;
        $display("Number: %b, Segments: %b", w, d);

        // 2
        w = 4'b0010; #10;
        $display("Number: %b, Segments: %b", w, d);

        // 3
        w = 4'b0011; #10;
        $display("Number: %b, Segments: %b", w, d);

        // 4
        w = 4'b0100; #10;
        $display("Number: %b, Segments: %b", w, d);

        // 5
        w = 4'b0101; #10;
        $display("Number: %b, Segments: %b", w, d);
        
        // 6
        w = 4'b0110; #10;
        $display("Number: %b, Segments: %b", w, d);
        
        // 7
        w = 4'b0111; #10;
        $display("Number: %b, Segments: %b", w, d);

        // 8
        w = 4'b1000; #10;
        $display("Number: %b, Segments: %b", w, d);

        // 9
        w = 4'b1001; #10;
        $display("Number: %b, Segments: %b", w, d);
    end

    initial begin
        // Guardar el archivo de simulación en formato VCD
        $dumpfile("seg_decoder_tb.vcd");
        $dumpvars(0, seg_decoder_tb);  // Nombre correcto del módulo de prueba
    end
endmodule

Source/build/seg_decoder_tb.vcd
$date
	Wed Mar 26 18:24:57 2025
$end
$version
	Icarus Verilog
$end
$timescale
	1ps
$end
$scope module seg_decoder_tb $end
$var wire 7 ! d [6:0] $end
$var reg 4 " w [3:0] $end
$scope module uut $end
$var wire 4 # w [3:0] $end
$var wire 7 $ d [6:0] $end
$upscope $end
$upscope $end
$enddefinitions $end
$comment Show the parameter values. $end
$dumpall
$end
#0
$dumpvars
b1111110 $
b0 #
b0 "
b1111110 !
$end
#10000
b110000 !
b110000 $
b1 "
b1 #
#20000
b1101101 !
b1101101 $
b10 "
b10 #
#30000
b1111001 !
b1111001 $
b11 "
b11 #
#40000
b110011 !
b110011 $
b100 "
b100 #
#50000
b1011011 !
b1011011 $
b101 "
b101 #
#60000
b1111101 !
b1111101 $
b110 "
b110 #
#70000
b1110000 !
b1110000 $
b111 "
b111 #
#80000
b1111111 !
b1111111 $
b1000 "
b1000 #
#90000
b1110011 !
b1110011 $
b1001 "
b1001 #
