Source/design/seg_decoder.sv
`timescale 1ns/1ps
// Este modulo recibe un numero binario de 4 bits retorna 7 bits, uno para cada segmentos del display

module seg_decoder(input logic [3:0] w, output logic [6:0] d);
    assign d[6] =  w[1] | w[3] | (~w[2] & ~w[0]) | (w[2] & w[0]);   // a
    assign d[5] = ~w[2] | w[1] | ~w[0];                            // b
    assign d[4] = ~w[1] | w[2] | w[0];                             // c
    assign d[3] = (~w[2] & ~w[0]) | (~w[2] & w[1]) + (w[1] & ~w[0]) | (w[2] & ~w[1] & w[0]) ;  // d
    assign d[2] = (~w[2] & ~w[0]) | (w[1] & ~w[0]);                // e
    assign d[1] = w[3] | (~w[1] & ~w[0]) | (w[2] & ~w[1]);         // f
    assign d[0] = w[3] | (~w[2] & w[1]) | (w[2] & ~w[0]) | (w[2] & ~w[1]);  // g
endmodule

Source/design/mux.sv
`timescale 1ns/1ps
// Este modulo recibe una señal de una frecuencia que se elije, un numero binario que se lee 
// del dipswitch de 4 pines y recibe el sindrome.
// Dependiendo del estado de la señal de reloj, el mux selecciona el numero binario o el sindrome.


module mux(
    input logic clk_out,    // Señal de reloj de 1 kHz (selector)
    input logic [3:0] i,    // Entrada 0 (4 bits)
    input logic [3:0] p,    // Entrada 1 (4 bits)
    output logic [3:0] w    // Salida (4 bits)
);

    always_comb begin
        w = (clk_out) ? p : i; // Si clk_1kHz = 1 -> p, sino -> i
    end

endmodule

Source/design/freq_div.sv
`timescale 1ns/1ps
// Este modulo es un divisor de frecuencia, el cual implenta un contador para determinar los momentos en los 
// en los que se debe conmutar la señal para que dicha señal sea de la frecuencia que se desea



module freq_div(
    input logic clk,       // Signal de reloj interno 27 MHz
    output logic clk_out,  // Signal de frecuencia deseada
    output logic x,        // Signal de control de bjt x
    output logic y);       // Signal de control de bjt y

    parameter frequency = 27_000_000;                   // Frecuencia de entrada (27 MHz)
    parameter freq_out = 500;                         // Frecuencia de salida ajustable
    parameter max_count = frequency / (2 * freq_out);   // La cuenta maxima del contador

    logic [24:0] count;  // Tamaño suficiente para almacenar max_count

    // Inicialización de los valores iniciales
    initial begin
        count = 0;
        clk_out = 0;
        x=0;
        y=1;
    end

    // Lógica para contar y generar clk_out
    always @(posedge clk) begin    // posedge clk -> flancos de subida de clk
        if (count == max_count - 1) begin
            // Se conmutan las señales de salida
            clk_out <= ~clk_out;
            x <= ~x;             
            y <= ~y;
            count <= 0;
        end 
        else begin
            count <= count + 1;
        end
    end
endmodule

Source/design/ham_decoder.sv
`timescale 1ns/1ps
// Este modulo recibe un numero binario codificado con Hamming y retorna el sindrome

module ham_decoder(
    input logic [6:0] e, 
    output logic [3:0] p, 
    output logic [3:0] c);

    // El sindrome es de 3 bits, pero se le agrega un 0 como cuarto bit para que 
    // funcione como entrada del decoder del display 
    
    assign p[3] = 1'b0;      
    assign p[2] = e[3] ^ e[6] ^ e[5] ^ e[4];
    assign p[1] = e[1] ^ e[6] ^ e[5] ^ e[2];
    assign p[0] = e[0] ^ e[6] ^ e[4] ^ e[2];

        // Señal interna para la palabra corregida
    logic [6:0] corrected_e;

    assign corrected_e[0] = (p[2:0] == 3'b001) ? ~e[0] : e[0];
    assign corrected_e[1] = (p[2:0] == 3'b010) ? ~e[1] : e[1];
    assign corrected_e[2] = (p[2:0] == 3'b011) ? ~e[2] : e[2];
    assign corrected_e[3] = (p[2:0] == 3'b100) ? ~e[3] : e[3];
    assign corrected_e[4] = (p[2:0] == 3'b101) ? ~e[4] : e[4];
    assign corrected_e[5] = (p[2:0] == 3'b110) ? ~e[5] : e[5];
    assign corrected_e[6] = (p[2:0] == 3'b111) ? ~e[6] : e[6];

    // Extraer los bits de datos correctos
    assign c = ~{corrected_e[6], corrected_e[5], corrected_e[4], corrected_e[2]};

endmodule

Source/design/top.sv
`timescale 1ns/1ps

module top(
    //input logic module_inputs //Recibe los valores de los Pins
    input logic clk,
    input logic [3:0] i,   // Numero binario
    input logic [6:0] e,   // Numero binario codificado
    output logic [6:0] d,  // Segmentos
    output logic [3:0] c,  // Palabra corregida
    output logic x,        // Control de bjt
    output logic y);       // Control de bjt

    // Declaracion 
    logic [3:0] p;   // Sindrome
    logic [3:0] w;   // Numero binario
    logic clk_out;   // Reloj 1kHz
    ////////////////////////////

    // Instaciamiento de los modulos
    ham_decoder ham (.e(e), .p(p), .c(c));
    freq_div freq (.clk(clk), .clk_out(clk_out), .x(x), .y(y));
    mux mux (.clk_out(clk_out), .i(i), .p(p), .w(w));
    seg_decoder bcd (.w(w), .d(d));
    ////////////////////////////

endmodule

Source/sim/top_tb.sv
`timescale 1ns/1ps


module top_tb;

    // Declaracion de entradas
    logic [3:0] i;   // Numero binario
    logic [6:0] e;   // Numero binario codificado con hamming
    logic clk;       // Reloj 27 MHz

    // Declaracion de salidas
    logic [6:0] d; // Segmentos del display
    logic [3:0] c;  // Palabra corregida
    logic x;
    logic y;  

    ////////////////////////////


    // Instaciamiento de los modulos
    top uut(.clk(clk), .i(i), .e(e), .d(d), .c(c), .x(x), .y(y));
    ////////////////////////////

    always begin
        #18.5 clk = ~clk;  // T = 1 / 27 MHz => periodo = 37ns, cada mitad del periodo 18.5ns
    end

    initial begin
        clk=0;
        i = 4'b0101; // Numero binario
        e = 7'b1100110; // Numero binario codificado error en bit 5
        $monitor("Reloj: %t, Segmentos: %b, Correccion: %b", $time, d, c);

        
        #3000000; // Simular por 3 ms
        $finish;
    end


    // Generación del archivo VCD
    initial begin
        $dumpfile("top_tb.vcd");
        $dumpvars(0, top_tb);
    end


endmodule

Source/build/top_tb.vcd
$date
	Tue Apr 01 08:22:36 2025
$end
$version
	Icarus Verilog
$end
$timescale
	1ps
$end
$scope module top_tb $end
$var wire 1 ! y $end
$var wire 1 " x $end
$var wire 7 # d [6:0] $end
$var wire 4 $ c [3:0] $end
$var reg 1 % clk $end
$var reg 7 & e [6:0] $end
$var reg 4 ' i [3:0] $end
$scope module uut $end
$var wire 1 % clk $end
$var wire 7 ( e [6:0] $end
$var wire 4 ) i [3:0] $end
$var wire 1 ! y $end
$var wire 1 " x $end
$var wire 4 * w [3:0] $end
$var wire 4 + p [3:0] $end
$var wire 7 , d [6:0] $end
$var wire 1 - clk_out $end
$var wire 4 . c [3:0] $end
$scope module bcd $end
$var wire 4 / w [3:0] $end
$var wire 7 0 d [6:0] $end
$upscope $end
$scope module freq $end
$var wire 1 % clk $end
$var parameter 32 1 freq_out $end
$var parameter 32 2 frequency $end
$var parameter 64 3 max_count $end
$var reg 1 - clk_out $end
$var reg 25 4 count [24:0] $end
$var reg 1 " x $end
$var reg 1 ! y $end
$upscope $end
$scope module ham $end
$var wire 4 5 c [3:0] $end
$var wire 7 6 e [6:0] $end
$var wire 4 7 p [3:0] $end
$var wire 7 8 corrected_e [6:0] $end
$upscope $end
$scope module mux $end
$var wire 1 - clk_out $end
$var wire 4 9 i [3:0] $end
$var wire 4 : p [3:0] $end
$var reg 4 ; w [3:0] $end
$upscope $end
$upscope $end
$upscope $end
$enddefinitions $end
$comment Show the parameter values. $end
$dumpall
b110100101111000 3
b1100110111111110011000000 2
b111110100 1
$end
#0
$dumpvars
b101 ;
b0 :
b101 9
b1100110 8
b0 7
b1100110 6
b10 5
b0 4
b1011011 0
b101 /
b10 .
0-
b1011011 ,
b0 +
b101 *
b101 )
b1100110 (
b101 '
b1100110 &
0%
b10 $
b1011011 #
0"
1!
$end
#18500
b1 4
1%
#37000
0%
#55500
b10 4
1%
#74000
0%
#92500
b11 4
1%
#111000
0%
#129500
b100 4
1%
#148000
0%
#166500
b101 4
1%
#185000
0%
#203500
b110 4
1%
#222000
0%
#240500
b111 4
1%
#259000
0%
#277500
b1000 4
1%
#296000
0%
#314500
b1001 4
1%
#333000
0%
#351500
b1010 4
1%
#370000
0%
#388500
b1011 4
1%
#407000
0%
#425500
b1100 4
1%
#444000
0%
#462500
b1101 4
1%
#481000
0%
#499500
b1110 4
1%
#518000
0%
#536500
b1111 4
1%
#555000
0%
#573500
b10000 4
1%
#592000
0%
#610500
b10001 4
1%
#629000
0%
#647500
b10010 4
1%
#666000
0%
#684500
b10011 4
1%
#703000
0%
#721500
b10100 4
1%
#740000
0%
#758500
b10101 4
1%
#777000
0%
#795500
b10110 4
1%
#814000
0%
#832500
b10111 4
1%
#851000
0%
#869500
b11000 4
1%
#888000
0%
#906500
b11001 4
1%
#925000
0%
#943500
b11010 4
1%
#962000
0%
#980500
b11011 4
1%
#999000
0%
#1017500
b11100 4
1%
#1036000
0%
#1054500
b11101 4
1%
#1073000
0%
#1091500
b11110 4
1%
#1110000
0%
#1128500
b11111 4
1%
#1147000
0%
#1165500
b100000 4
1%
#1184000
0%
#1202500
b100001 4
1%
#1221000
0%
#1239500
b100010 4
1%
#1258000
0%
#1276500
b100011 4
1%
#1295000
0%
#1313500
b100100 4
1%
#1332000
0%
#1350500
b100101 4
1%
#1369000
0%
#1387500
b100110 4
1%
#1406000
0%
#1424500
b100111 4
1%
#1443000
0%
#1461500
b101000 4
1%
#1480000
0%
#1498500
b101001 4
1%
#1517000
0%
#1535500
b101010 4
1%
#1554000
0%
#1572500
b101011 4
1%
#1591000
0%
#1609500
b101100 4
1%
#1628000
0%
#1646500
b101101 4
1%
#1665000
0%
#1683500
b101110 4
1%
#1702000
0%
#1720500
b101111 4
1%
#1739000
0%
#1757500
b110000 4
1%
#1776000
0%
#1794500
b110001 4
1%
#1813000
0%
#1831500
b110010 4
1%
#1850000
0%
#1868500
b110011 4
1%
#1887000
0%
#1905500
b110100 4
1%
#1924000
0%
#1942500
b110101 4
1%
#1961000
0%
#1979500
b110110 4
1%
#1998000
0%
#2016500
b110111 4
1%
#2035000
0%
#2053500
b111000 4
1%
#2072000
0%
#2090500
b111001 4
1%
#2109000
0%
#2127500
b111010 4
1%
#2146000
0%
#2164500
b111011 4
1%
#2183000
0%
#2201500
b111100 4
1%
#2220000
0%
#2238500
b111101 4
1%
#2257000
0%
#2275500
b111110 4
1%
#2294000
0%
#2312500
b111111 4
1%
#2331000
0%
#2349500
b1000000 4
1%
#2368000
0%
#2386500
b1000001 4
1%
#2405000
0%
#2423500
b1000010 4
1%
#2442000
0%
#2460500
b1000011 4
1%
#2479000
0%
#2497500
b1000100 4
1%
#2516000
0%
#2534500
b1000101 4
1%
#2553000
0%
#2571500
b1000110 4
1%
#2590000
0%
#2608500
b1000111 4
1%
#2627000
0%
#2645500
b1001000 4
1%
#2664000
0%
#2682500
b1001001 4
1%
#2701000
0%
#2719500
b1001010 4
1%
#2738000
0%
#2756500
b1001011 4
1%
#2775000
0%
#2793500
b1001100 4
1%
#2812000
0%
#2830500
b1001101 4
1%
#2849000
0%
#2867500
b1001110 4
1%
#2886000
0%
#2904500
b1001111 4
1%
#2923000
0%
#2941500
b1010000 4
1%
#2960000
0%
#2978500
b1010001 4
1%
#2997000
0%
#3015500
b1010010 4
1%
#3034000
0%
#3052500
b1010011 4
1%
#3071000
0%
#3089500
b1010100 4
1%
#3108000
0%
#3126500
b1010101 4
1%
#3145000
0%
#3163500
b1010110 4
1%
#3182000
0%
#3200500
b1010111 4
1%
#3219000
0%
#3237500
b1011000 4
1%
#3256000
0%
#3274500
b1011001 4
1%
#3293000
0%
#3311500
b1011010 4
1%
#3330000
0%
#3348500
b1011011 4
1%
#3367000
0%
#3385500
b1011100 4
1%
#3404000
0%
#3422500
b1011101 4
1%
#3441000
0%
#3459500
b1011110 4
1%
#3478000
0%
#3496500
b1011111 4
1%
#3515000
0%
#3533500
b1100000 4
1%
#3552000
0%
#3570500
b1100001 4
1%
#3589000
0%
#3607500
b1100010 4
1%
#3626000
0%
#3644500
b1100011 4
1%
#3663000
0%
#3681500
b1100100 4
1%
#3700000
0%
#3718500
b1100101 4
1%
#3737000
0%
#3755500
b1100110 4
1%
#3774000
0%
#3792500
b1100111 4
1%
#3811000
0%
#3829500
b1101000 4
1%
#3848000
0%
#3866500
b1101001 4
1%
#3885000
0%
#3903500
b1101010 4
1%
#3922000
0%
#3940500
b1101011 4
1%
#3959000
0%
#3977500
b1101100 4
1%
#3996000
0%
#4014500
b1101101 4
1%
#4033000
0%
#4051500
b1101110 4
1%
#4070000
0%
#4088500
b1101111 4
1%
#4107000
0%
#4125500
b1110000 4
1%
#4144000
0%
#4162500
b1110001 4
1%
#4181000
0%
#4199500
b1110010 4
1%
#4218000
0%
#4236500
b1110011 4
1%
#4255000
0%
#4273500
b1110100 4
1%
#4292000
0%
#4310500
b1110101 4
1%
#4329000
0%
#4347500
b1110110 4
1%
#4366000
0%
#4384500
b1110111 4
1%
#4403000
0%
#4421500
b1111000 4
1%
#4440000
0%
#4458500
b1111001 4
1%
#4477000
0%
#4495500
b1111010 4
1%
#4514000
0%
#4532500
b1111011 4
1%
#4551000
0%
#4569500
b1111100 4
1%
#4588000
0%
#4606500
b1111101 4
1%
#4625000
0%
#4643500
b1111110 4
1%
#4662000
0%
#4680500
b1111111 4
1%
#4699000
0%
#4717500
b10000000 4
1%
#4736000
0%
#4754500
b10000001 4
1%
#4773000
0%
#4791500
b10000010 4
1%
#4810000
0%
#4828500
b10000011 4
1%
#4847000
0%
#4865500
b10000100 4
1%
#4884000
0%
#4902500
b10000101 4
1%
#4921000
0%
#4939500
b10000110 4
1%
#4958000
0%
#4976500
b10000111 4
1%
#4995000
0%
#5013500
b10001000 4
1%
#5032000
0%
#5050500
b10001001 4
1%
#5069000
0%
#5087500
b10001010 4
1%
#5106000
0%
#5124500
b10001011 4
1%
#5143000
0%
#5161500
b10001100 4
1%
#5180000
0%
#5198500
b10001101 4
1%
#5217000
0%
#5235500
b10001110 4
1%
#5254000
0%
#5272500
b10001111 4
1%
#5291000
0%
#5309500
b10010000 4
1%
#5328000
0%
#5346500
b10010001 4
1%
#5365000
0%
#5383500
b10010010 4
1%
#5402000
0%
#5420500
b10010011 4
1%
#5439000
0%
#5457500
b10010100 4
1%
#5476000
0%
#5494500
b10010101 4
1%
#5513000
0%
#5531500
b10010110 4
1%
#5550000
0%
#5568500
b10010111 4
1%
#5587000
0%
#5605500
b10011000 4
1%
#5624000
0%
#5642500
b10011001 4
1%
#5661000
0%
#5679500
b10011010 4
1%
#5698000
0%
#5716500
b10011011 4
1%
#5735000
0%
#5753500
b10011100 4
1%
#5772000
0%
#5790500
b10011101 4
1%
#5809000
0%
#5827500
b10011110 4
1%
#5846000
0%
#5864500
b10011111 4
1%
#5883000
0%
#5901500
b10100000 4
1%
#5920000
0%
#5938500
b10100001 4
1%
#5957000
0%
#5975500
b10100010 4
1%
#5994000
0%
#6012500
b10100011 4
1%
#6031000
0%
#6049500
b10100100 4
1%
#6068000
0%
#6086500
b10100101 4
1%
#6105000
0%
#6123500
b10100110 4
1%
#6142000
0%
#6160500
b10100111 4
1%
#6179000
0%
#6197500
b10101000 4
1%
#6216000
0%
#6234500
b10101001 4
1%
#6253000
0%
#6271500
b10101010 4
1%
#6290000
0%
#6308500
b10101011 4
1%
#6327000
0%
#6345500
b10101100 4
1%
#6364000
0%
#6382500
b10101101 4
1%
#6401000
0%
#6419500
b10101110 4
1%
#6438000
0%
#6456500
b10101111 4
1%
#6475000
0%
#6493500
b10110000 4
1%
#6512000
0%
#6530500
b10110001 4
1%
#6549000
0%
#6567500
b10110010 4
1%
#6586000
0%
#6604500
b10110011 4
1%
#6623000
0%
#6641500
b10110100 4
1%
#6660000
0%
#6678500
b10110101 4
1%
#6697000
0%
#6715500
b10110110 4
1%
#6734000
0%
#6752500
b10110111 4
1%
#6771000
0%
#6789500
b10111000 4
1%
#6808000
0%
#6826500
b10111001 4
1%
#6845000
0%
#6863500
b10111010 4
1%
#6882000
0%
#6900500
b10111011 4
1%
#6919000
0%
#6937500
b10111100 4
1%
#6956000
0%
#6974500
b10111101 4
1%
#6993000
0%
#7011500
b10111110 4
1%
#7030000
0%
#7048500
b10111111 4
1%
#7067000
0%
#7085500
b11000000 4
1%
#7104000
0%
#7122500
b11000001 4
1%
#7141000
0%
#7159500
b11000010 4
1%
#7178000
0%
#7196500
b11000011 4
1%
#7215000
0%
#7233500
b11000100 4
1%
#7252000
0%
#7270500
b11000101 4
1%
#7289000
0%
#7307500
b11000110 4
1%
#7326000
0%
#7344500
b11000111 4
1%
#7363000
0%
#7381500
b11001000 4
1%
#7400000
0%
#7418500
b11001001 4
1%
#7437000
0%
#7455500
b11001010 4
1%
#7474000
0%
#7492500
b11001011 4
1%
#7511000
0%
#7529500
b11001100 4
1%
#7548000
0%
#7566500
b11001101 4
1%
#7585000
0%
#7603500
b11001110 4
1%
#7622000
0%
#7640500
b11001111 4
1%
#7659000
0%
#7677500
b11010000 4
1%
#7696000
0%
#7714500
b11010001 4
1%
#7733000
0%
#7751500
b11010010 4
1%
#7770000
0%
#7788500
b11010011 4
1%
#7807000
0%
#7825500
b11010100 4
1%
#7844000
0%
#7862500
b11010101 4
1%
#7881000
0%
#7899500
b11010110 4
1%
#7918000
0%
#7936500
b11010111 4
1%
#7955000
0%
#7973500
b11011000 4
1%
#7992000
0%
#8010500
b11011001 4
1%
#8029000
0%
#8047500
b11011010 4
1%
#8066000
0%
#8084500
b11011011 4
1%
#8103000
0%
#8121500
b11011100 4
1%
#8140000
0%
#8158500
b11011101 4
1%
#8177000
0%
#8195500
b11011110 4
1%
#8214000
0%
#8232500
b11011111 4
1%
#8251000
0%
#8269500
b11100000 4
1%
#8288000
0%
#8306500
b11100001 4
1%
#8325000
0%
#8343500
b11100010 4
1%
#8362000
0%
#8380500
b11100011 4
1%
#8399000
0%
#8417500
b11100100 4
1%
#8436000
0%
#8454500
b11100101 4
1%
#8473000
0%
#8491500
b11100110 4
1%
#8510000
0%
#8528500
b11100111 4
1%
#8547000
0%
#8565500
b11101000 4
1%
#8584000
0%
#8602500
b11101001 4
1%
#8621000
0%
#8639500
b11101010 4
1%
#8658000
0%
#8676500
b11101011 4
1%
#8695000
0%
#8713500
b11101100 4
1%
#8732000
0%
#8750500
b11101101 4
1%
#8769000
0%
#8787500
b11101110 4
1%
#8806000
0%
#8824500
b11101111 4
1%
#8843000
0%
#8861500
b11110000 4
1%
#8880000
0%
#8898500
b11110001 4
1%
#8917000
0%
#8935500
b11110010 4
1%
#8954000
0%
#8972500
b11110011 4
1%
#8991000
0%
#9009500
b11110100 4
1%
#9028000
0%
#9046500
b11110101 4
1%
#9065000
0%
#9083500
b11110110 4
1%
#9102000
0%
#9120500
b11110111 4
1%
#9139000
0%
#9157500
b11111000 4
1%
#9176000
0%
#9194500
b11111001 4
1%
#9213000
0%
#9231500
b11111010 4
1%
#9250000
0%
#9268500
b11111011 4
1%
#9287000
0%
#9305500
b11111100 4
1%
#9324000
0%
#9342500
b11111101 4
1%
#9361000
0%
#9379500
b11111110 4
1%
#9398000
0%
#9416500
b11111111 4
1%
#9435000
0%
#9453500
b100000000 4
1%
#9472000
0%
#9490500
b100000001 4
1%
#9509000
0%
#9527500
b100000010 4
1%
#9546000
0%
#9564500
b100000011 4
1%
#9583000
0%
#9601500
b100000100 4
1%
#9620000
0%
#9638500
b100000101 4
1%
#9657000
0%
#9675500
b100000110 4
1%
#9694000
0%
#9712500
b100000111 4
1%
#9731000
0%
#9749500
b100001000 4
1%
#9768000
0%
#9786500
b100001001 4
1%
#9805000
0%
#9823500
b100001010 4
1%
#9842000
0%
#9860500
b100001011 4
1%
#9879000
0%
#9897500
b100001100 4
1%
#9916000
0%
#9934500
b100001101 4
1%
#9953000
0%
#9971500
b100001110 4
1%
#9990000
0%
#10008500
b100001111 4
1%
#10027000
0%
#10045500
b100010000 4
1%
#10064000
0%
#10082500
b100010001 4
1%
#10101000
0%
#10119500
b100010010 4
1%
#10138000
0%
#10156500
b100010011 4
1%
#10175000
0%
#10193500
b100010100 4
1%
#10212000
0%
#10230500
b100010101 4
1%
#10249000
0%
#10267500
b100010110 4
1%
#10286000
0%
#10304500
b100010111 4
1%
#10323000
0%
#10341500
b100011000 4
1%
#10360000
0%
#10378500
b100011001 4
1%
#10397000
0%
#10415500
b100011010 4
1%
#10434000
0%
#10452500
b100011011 4
1%
#10471000
0%
#10489500
b100011100 4
1%
#10508000
0%
#10526500
b100011101 4
1%
#10545000
0%
#10563500
b100011110 4
1%
#10582000
0%
#10600500
b100011111 4
1%
#10619000
0%
#10637500
b100100000 4
1%
#10656000
0%
#10674500
b100100001 4
1%
#10693000
0%
#10711500
b100100010 4
1%
#10730000
0%
#10748500
b100100011 4
1%
#10767000
0%
#10785500
b100100100 4
1%
#10804000
0%
#10822500
b100100101 4
1%
#10841000
0%
#10859500
b100100110 4
1%
#10878000
0%
#10896500
b100100111 4
1%
#10915000
0%
#10933500
b100101000 4
1%
#10952000
0%
#10970500
b100101001 4
1%
#10989000
0%
#11007500
b100101010 4
1%
#11026000
0%
#11044500
b100101011 4
1%
#11063000
0%
#11081500
b100101100 4
1%
#11100000
0%
#11118500
b100101101 4
1%
#11137000
0%
#11155500
b100101110 4
1%
#11174000
0%
#11192500
b100101111 4
1%
#11211000
0%
#11229500
b100110000 4
1%
#11248000
0%
#11266500
b100110001 4
1%
#11285000
0%
#11303500
b100110010 4
1%
#11322000
0%
#11340500
b100110011 4
1%
#11359000
0%
#11377500
b100110100 4
1%
#11396000
0%
#11414500
b100110101 4
1%
#11433000
0%
#11451500
b100110110 4
1%
#11470000
0%
#11488500
b100110111 4
1%
#11507000
0%
#11525500
b100111000 4
1%
#11544000
0%
#11562500
b100111001 4
1%
#11581000
0%
#11599500
b100111010 4
1%
#11618000
0%
#11636500
b100111011 4
1%
#11655000
0%
#11673500
b100111100 4
1%
#11692000
0%
#11710500
b100111101 4
1%
#11729000
0%
#11747500
b100111110 4
1%
#11766000
0%
#11784500
b100111111 4
1%
#11803000
0%
#11821500
b101000000 4
1%
#11840000
0%
#11858500
b101000001 4
1%
#11877000
0%
#11895500
b101000010 4
1%
#11914000
0%
#11932500
b101000011 4
1%
#11951000
0%
#11969500
b101000100 4
1%
#11988000
0%
#12006500
b101000101 4
1%
#12025000
0%
#12043500
b101000110 4
1%
#12062000
0%
#12080500
b101000111 4
1%
#12099000
0%
#12117500
b101001000 4
1%
#12136000
0%
#12154500
b101001001 4
1%
#12173000
0%
#12191500
b101001010 4
1%
#12210000
0%
#12228500
b101001011 4
1%
#12247000
0%
#12265500
b101001100 4
1%
#12284000
0%
#12302500
b101001101 4
1%
#12321000
0%
#12339500
b101001110 4
1%
#12358000
0%
#12376500
b101001111 4
1%
#12395000
0%
#12413500
b101010000 4
1%
#12432000
0%
#12450500
b101010001 4
1%
#12469000
0%
#12487500
b101010010 4
1%
#12506000
0%
#12524500
b101010011 4
1%
#12543000
0%
#12561500
b101010100 4
1%
#12580000
0%
#12598500
b101010101 4
1%
#12617000
0%
#12635500
b101010110 4
1%
#12654000
0%
#12672500
b101010111 4
1%
#12691000
0%
#12709500
b101011000 4
1%
#12728000
0%
#12746500
b101011001 4
1%
#12765000
0%
#12783500
b101011010 4
1%
#12802000
0%
#12820500
b101011011 4
1%
#12839000
0%
#12857500
b101011100 4
1%
#12876000
0%
#12894500
b101011101 4
1%
#12913000
0%
#12931500
b101011110 4
1%
#12950000
0%
#12968500
b101011111 4
1%
#12987000
0%
#13005500
b101100000 4
1%
#13024000
0%
#13042500
b101100001 4
1%
#13061000
0%
#13079500
b101100010 4
1%
#13098000
0%
#13116500
b101100011 4
1%
#13135000
0%
#13153500
b101100100 4
1%
#13172000
0%
#13190500
b101100101 4
1%
#13209000
0%
#13227500
b101100110 4
1%
#13246000
0%
#13264500
b101100111 4
1%
#13283000
0%
#13301500
b101101000 4
1%
#13320000
0%
#13338500
b101101001 4
1%
#13357000
0%
#13375500
b101101010 4
1%
#13394000
0%
#13412500
b101101011 4
1%
#13431000
0%
#13449500
b101101100 4
1%
#13468000
0%
#13486500
b101101101 4
1%
#13505000
0%
#13523500
b101101110 4
1%
#13542000
0%
#13560500
b101101111 4
1%
#13579000
0%
#13597500
b101110000 4
1%
#13616000
0%
#13634500
b101110001 4
1%
#13653000
0%
#13671500
b101110010 4
1%
#13690000
0%
#13708500
b101110011 4
1%
#13727000
0%
#13745500
b101110100 4
1%
#13764000
0%
#13782500
b101110101 4
1%
#13801000
0%
#13819500
b101110110 4
1%
#13838000
0%
#13856500
b101110111 4
1%
#13875000
0%
#13893500
b101111000 4
1%
#13912000
0%
#13930500
b101111001 4
1%
#13949000
0%
#13967500
b101111010 4
1%
#13986000
0%
#14004500
b101111011 4
1%
#14023000
0%
#14041500
b101111100 4
1%
#14060000
0%
#14078500
b101111101 4
1%
#14097000
0%
#14115500
b101111110 4
1%
#14134000
0%
#14152500
b101111111 4
1%
#14171000
0%
#14189500
b110000000 4
1%
#14208000
0%
#14226500
b110000001 4
1%
#14245000
0%
#14263500
b110000010 4
1%
#14282000
0%
#14300500
b110000011 4
1%
#14319000
0%
#14337500
b110000100 4
1%
#14356000
0%
#14374500
b110000101 4
1%
#14393000
0%
#14411500
b110000110 4
1%
#14430000
0%
#14448500
b110000111 4
1%
#14467000
0%
#14485500
b110001000 4
1%
#14504000
0%
#14522500
b110001001 4
1%
#14541000
0%
#14559500
b110001010 4
1%
#14578000
0%
#14596500
b110001011 4
1%
#14615000
0%
#14633500
b110001100 4
1%
#14652000
0%
#14670500
b110001101 4
1%
#14689000
0%
#14707500
b110001110 4
1%
#14726000
0%
#14744500
b110001111 4
1%
#14763000
0%
#14781500
b110010000 4
1%
#14800000
0%
#14818500
b110010001 4
1%
#14837000
0%
#14855500
b110010010 4
1%
#14874000
0%
#14892500
b110010011 4
1%
#14911000
0%
#14929500
b110010100 4
1%
#14948000
0%
#14966500
b110010101 4
1%
#14985000
0%
#15003500
b110010110 4
1%
#15022000
0%
#15040500
b110010111 4
1%
#15059000
0%
#15077500
b110011000 4
1%
#15096000
0%
#15114500
b110011001 4
1%
#15133000
0%
#15151500
b110011010 4
1%
#15170000
0%
#15188500
b110011011 4
1%
#15207000
0%
#15225500
b110011100 4
1%
#15244000
0%
#15262500
b110011101 4
1%
#15281000
0%
#15299500
b110011110 4
1%
#15318000
0%
#15336500
b110011111 4
1%
#15355000
0%
#15373500
b110100000 4
1%
#15392000
0%
#15410500
b110100001 4
1%
#15429000
0%
#15447500
b110100010 4
1%
#15466000
0%
#15484500
b110100011 4
1%
#15503000
0%
#15521500
b110100100 4
1%
#15540000
0%
#15558500
b110100101 4
1%
#15577000
0%
#15595500
b110100110 4
1%
#15614000
0%
#15632500
b110100111 4
1%
#15651000
0%
#15669500
b110101000 4
1%
#15688000
0%
#15706500
b110101001 4
1%
#15725000
0%
#15743500
b110101010 4
1%
#15762000
0%
#15780500
b110101011 4
1%
#15799000
0%
#15817500
b110101100 4
1%
#15836000
0%
#15854500
b110101101 4
1%
#15873000
0%
#15891500
b110101110 4
1%
#15910000
0%
#15928500
b110101111 4
1%
#15947000
0%
#15965500
b110110000 4
1%
#15984000
0%
#16002500
b110110001 4
1%
#16021000
0%
#16039500
b110110010 4
1%
#16058000
0%
#16076500
b110110011 4
1%
#16095000
0%
#16113500
b110110100 4
1%
#16132000
0%
#16150500
b110110101 4
1%
#16169000
0%
#16187500
b110110110 4
1%
#16206000
0%
#16224500
b110110111 4
1%
#16243000
0%
#16261500
b110111000 4
1%
#16280000
0%
#16298500
b110111001 4
1%
#16317000
0%
#16335500
b110111010 4
1%
#16354000
0%
#16372500
b110111011 4
1%
#16391000
0%
#16409500
b110111100 4
1%
#16428000
0%
#16446500
b110111101 4
1%
#16465000
0%
#16483500
b110111110 4
1%
#16502000
0%
#16520500
b110111111 4
1%
#16539000
0%
#16557500
b111000000 4
1%
#16576000
0%
#16594500
b111000001 4
1%
#16613000
0%
#16631500
b111000010 4
1%
#16650000
0%
#16668500
b111000011 4
1%
#16687000
0%
#16705500
b111000100 4
1%
#16724000
0%
#16742500
b111000101 4
1%
#16761000
0%
#16779500
b111000110 4
1%
#16798000
0%
#16816500
b111000111 4
1%
#16835000
0%
#16853500
b111001000 4
1%
#16872000
0%
#16890500
b111001001 4
1%
#16909000
0%
#16927500
b111001010 4
1%
#16946000
0%
#16964500
b111001011 4
1%
#16983000
0%
#17001500
b111001100 4
1%
#17020000
0%
#17038500
b111001101 4
1%
#17057000
0%
#17075500
b111001110 4
1%
#17094000
0%
#17112500
b111001111 4
1%
#17131000
0%
#17149500
b111010000 4
1%
#17168000
0%
#17186500
b111010001 4
1%
#17205000
0%
#17223500
b111010010 4
1%
#17242000
0%
#17260500
b111010011 4
1%
#17279000
0%
#17297500
b111010100 4
1%
#17316000
0%
#17334500
b111010101 4
1%
#17353000
0%
#17371500
b111010110 4
1%
#17390000
0%
#17408500
b111010111 4
1%
#17427000
0%
#17445500
b111011000 4
1%
#17464000
0%
#17482500
b111011001 4
1%
#17501000
0%
#17519500
b111011010 4
1%
#17538000
0%
#17556500
b111011011 4
1%
#17575000
0%
#17593500
b111011100 4
1%
#17612000
0%
#17630500
b111011101 4
1%
#17649000
0%
#17667500
b111011110 4
1%
#17686000
0%
#17704500
b111011111 4
1%
#17723000
0%
#17741500
b111100000 4
1%
#17760000
0%
#17778500
b111100001 4
1%
#17797000
0%
#17815500
b111100010 4
1%
#17834000
0%
#17852500
b111100011 4
1%
#17871000
0%
#17889500
b111100100 4
1%
#17908000
0%
#17926500
b111100101 4
1%
#17945000
0%
#17963500
b111100110 4
1%
#17982000
0%
#18000500
b111100111 4
1%
#18019000
0%
#18037500
b111101000 4
1%
#18056000
0%
#18074500
b111101001 4
1%
#18093000
0%
#18111500
b111101010 4
1%
#18130000
0%
#18148500
b111101011 4
1%
#18167000
0%
#18185500
b111101100 4
1%
#18204000
0%
#18222500
b111101101 4
1%
#18241000
0%
#18259500
b111101110 4
1%
#18278000
0%
#18296500
b111101111 4
1%
#18315000
0%
